nanomotif/__init__.py
nanomotif/_version.py
nanomotif/argparser.py
nanomotif/constants.py
nanomotif/dataload.py
nanomotif/datasets.py
nanomotif/fasta.py
nanomotif/find_motifs_bin.py
nanomotif/logger.py
nanomotif/main.py
nanomotif/model.py
nanomotif/motif.py
nanomotif/parallel.py
nanomotif/postprocess.py
nanomotif/seed.py
nanomotif/seq.py
nanomotif/utils.py
nanomotif/binnary/__init__.py
nanomotif/binnary/data_processing.py
nanomotif/binnary/detect_contamination.py
nanomotif/binnary/include_contigs.py
nanomotif/binnary/logging.py
nanomotif/binnary/utils.py
nanomotif/datasets/e_coli_assembly.polished.fasta
nanomotif/datasets/e_coli_bin-motifs.tsv
nanomotif/datasets/e_coli_contig-bin.tsv
nanomotif/datasets/geobacillus-contig-bin.tsv
nanomotif/datasets/geobacillus-plasmids.assembly.fasta
nanomotif/datasets/geobacillus-plasmids.bin-motifs.tsv
nanomotif/datasets/geobacillus-plasmids.motifs-scored.tsv
nanomotif/datasets/geobacillus-plasmids.motifs.tsv
nanomotif/datasets/geobacillus-plasmids.pileup.bed
nanomotif/datasets/geobacillus-plasmids.pileup.bed.gz
nanomotif/datasets/geobacillus-plasmids.pileup.bed.gz.tbi
nanomotif/datasets/test_pileup.bed
nanomotif/mtase_linker/MTase_linker.smk
nanomotif/mtase_linker/__init__.py
nanomotif/mtase_linker/command.py
nanomotif/mtase_linker/dependencies.py
nanomotif/mtase_linker/setup.smk
nanomotif/mtase_linker/envs/blast-2.14.1.yaml
nanomotif/mtase_linker/envs/defensefinder-2.0.0.yaml
nanomotif/mtase_linker/envs/prodigal-2.6.3.yaml
nanomotif/mtase_linker/envs/python_env-3.12.0.yaml
nanomotif/mtase_linker/src/blastp_processing.py
nanomotif/mtase_linker/src/extract_MTase_genes.py
nanomotif/mtase_linker/src/mod_typing.py
nanomotif/mtase_linker/src/motif_assignment.py
nanomotif/mtase_linker/src/utillities.py
nanomotif-1.1.1.dist-info/licenses/LICENSE
tests/__init__.py
tests/test_candidate.py
tests/test_cli_commands.py
tests/test_dataload.py
tests/test_fasta.py
tests/test_motif.py
tests/test_motif_find.py
tests/test_postprocess.py
tests/binnary/__init__.py
tests/binnary/conftest.py
nanomotif-1.1.1.dist-info/METADATA
nanomotif-1.1.1.dist-info/WHEEL
nanomotif-1.1.1.dist-info/entry_points.txt
nanomotif-1.1.1.dist-info/top_level.txt
nanomotif-1.1.1.dist-info/RECORD
