Metadata-Version: 2.4
Name: nanomotif
Version: 1.1.1
Summary: Identifying methlyation motifs in nanopore data
Author: AAU_DarkScience
Author-email: shei@bio.aau.com
License: MIT
License-File: LICENSE
Requires-Dist: wheel
Requires-Dist: requests
Requires-Dist: numpy<=2.0.0,>=1.24.4
Requires-Dist: pandas>=2.0.2
Requires-Dist: polars>=1.31
Requires-Dist: scipy>=1.10.1
Requires-Dist: scikit-learn>=1.5.2
Requires-Dist: networkx>=3.1
Requires-Dist: pyarrow>=15.0.2
Requires-Dist: epimetheus-py==0.7.5
Requires-Dist: hdbscan
Requires-Dist: Bio>=1.6.2
Requires-Dist: snakemake>=7.32.4
Requires-Dist: progressbar2>=3.53.1
Requires-Dist: pyfastx>=0.2.10
Requires-Dist: pysam>=0.22.0
Requires-Dist: regex>=2025.10.23
Requires-Dist: pyinstrument>=5.1.1
Dynamic: author
Dynamic: author-email
Dynamic: description
Dynamic: description-content-type
Dynamic: license
Dynamic: license-file
Dynamic: requires-dist
Dynamic: summary
